<?xml version="1.0" encoding="utf-8"?>
<question xmlns="http://www.gradians.com">
  <statement>
    <tex>\text{Find all points of discontinuity of f(x),\\
where f(x) is defined by }\\

\qquad f(x) = \begin{cases} 
         x+1,&amp;if \, x \geq 1\\
         x^2+1,&amp;if \, x\lt 1 
         \end{cases}</tex>
  </statement>
  <step>
    <context>
		\text{Does the following table accurately capture}\\
		\text{what we know about f(x)?}
		</context>
    <tex correct="true">
		\begin{tabular}{c|c|c|c}
		x &amp; f(x) &amp; \text{Defined?} &amp; \text{Continuous?} \\
		\hline
		x\lt 1 &amp; x^2 + 1 &amp;\text{Yes} &amp; \text{Yes} \\
		x = 1 &amp; x+1 &amp;\text{Yes} &amp; \text{Can't say} \\
		x\gt 1 &amp; x+1 &amp;\text{Yes} &amp; \text{Yes}
		\hline
		\end{tabular}
		</tex>
    <tex correct="false">
		\begin{tabular}{c|c|c|c}
		x &amp; f(x) &amp; \text{Defined?} &amp; \text{Continuous?} \\
		\hline
		x\lt 1 &amp; x^2 + 1 &amp;\text{Yes} &amp; \text{Yes} \\
		x = 1 &amp; x+1 &amp;\text{Yes} &amp; \text{Yes} \\
		x\gt 1 &amp; x+1 &amp;\text{Yes} &amp; \text{Yes}
		\hline
		\end{tabular}
		</tex>
    <reason>
		\text{For }x\lt 1, f(x) = x^2 + 1\text{ (parabolic curve).}\\
		\text{For }x\gt 1, f(x) = x+1 \text{ (straight line).} \\
		\text{Either way, f(x) is continuous for }x\neq 1.\\
		\text{The only problem point could be }x = 1\\
		\text{where the two curves meet - or don't meet.}
		</reason>
  </step>
  <step>
    <context>\text{What will be the condition for}\\
\text{continuity at }x=1 ?</context>
    <tex correct="true">\begin{align} 
          \lim_{x\to 1^-}(x^2+1) =\lim_{x\to 1^+}(x+1)  = f(1)
\end{align}</tex>
    <tex>\begin{align} 
          \lim_{x\to 1^-}(x^2+1) =\lim_{x\to 1^+}(x+1)
\end{align}</tex>
    <reason>
    \text{For a function to be continuous at a point}\\
    \textbf{two conditions}\text{ must be satisfied}\\
    \begin{tabular}{l|c}
    \hline
    \text{In English} &amp; \text{Mathematically} \\
    \hline
    \text{The function must approach} &amp; \\
    \text{the same value from the left } &amp; \\
    \text{and the right} &amp; 
    \lim_{x\to a}f(x)\text{ exists.}\\
    \text{And that value should be} &amp; \\
    \text{equal to the value of the} &amp; \\ 
    \text{function at that point} &amp; 
    \lim_{x\to a}f(x) = f(a) \\
    \hline
    \end{tabular}\\
    \text{This also means that wherever a function is}\\
    \text{continuous, it can be drawn without lifting}\\
    \text{the pencil.}
    </reason>
  </step>
  <step>
    <context>
		\text{Is the following true at }x = 1?
		</context>
    <tex correct="true">
		  \begin{tabular}{l|l|l|l}
		  \lim_{x\to 1^-}f(x) &amp; \lim_{x\to 1^+}f(x) &amp; f(x) &amp; \text{Continuous} \\
		  \hline
		  2 &amp; 2 &amp; 2 &amp; \text{Yes} \\
		  \hline
		  \end{tabular}
		</tex>
    <reason>
		\text{Be careful about which f(x) to use when}\\
		\text{calculating the left- and right-hand limits.}\\
		\text{For }x\geq 1, f(x) = x+1.\text{For }x\lt 1, f(x) = x^2+1. 
		</reason>
  </step>
  <choices>
    <tex>\text{Discontinuous everywhere in domain \\
of f(x)}</tex>
    <tex correct="true">\text{Continuous everywhere}</tex>
    <tex>\text{Discontinuous everywhere in domain \\
of f(x) except x=2}</tex>
    <tex>\text{x=1 is only point of discontinuity}</tex>
  </choices>
</question>
